msz_svr_conn/__init__.py
msz_svr_conn/connection.py
msz_svr_conn/exceptions.py
msz_svr_conn/version.py
tests/__init__.py
tests/test_api_connection.py
tests/test_connection_exceptions.py
msz_svr_conn-0.0.1.dist-info/LICENSE
msz_svr_conn-0.0.1.dist-info/METADATA
msz_svr_conn-0.0.1.dist-info/WHEEL
msz_svr_conn-0.0.1.dist-info/top_level.txt
msz_svr_conn-0.0.1.dist-info/RECORD
