Metadata-Version: 2.1
Name: msz-svr-conn
Version: 0.0.1
Summary: Server Connection
Home-page: https://gitlab.com/mesozi/market-force-360/msz-svr-conn
Author: Nyamu Kang'alia
Author-email: kangalia@mesozi.com
License: UNKNOWN
Platform: UNKNOWN
Classifier: Programming Language :: Python :: 3
Classifier: License :: OSI Approved :: MIT License
Classifier: Operating System :: OS Independent
Classifier: Topic :: Software Development :: Libraries
Classifier: Programming Language :: Python :: 3.7
Requires-Dist: requests[security]
